irradiapy/__init__.py
irradiapy/config.py
irradiapy/damagedb.py
irradiapy/dtypes.py
irradiapy/analysis/__init__.py
irradiapy/analysis/clusters.py
irradiapy/analysis/defects.py
irradiapy/analysis/defectsidentifier.py
irradiapy/analysis/dpa.py
irradiapy/io/__init__.py
irradiapy/io/bzip2lammpsreader.py
irradiapy/io/bzip2lammpswriter.py
irradiapy/io/lammpslogreader.py
irradiapy/io/lammpsreader.py
irradiapy/io/lammpsreadermpi.py
irradiapy/io/lammpswriter.py
irradiapy/io/lammpswritermpi.py
irradiapy/io/xyzreader.py
irradiapy/io/xyzwriter.py
irradiapy/materials/__init__.py
irradiapy/materials/ag.py
irradiapy/materials/cr.py
irradiapy/materials/cu.py
irradiapy/materials/fe.py
irradiapy/materials/material.py
irradiapy/materials/o.py
irradiapy/materials/w.py
irradiapy/srim/__init__.py
irradiapy/srim/analysis.py
irradiapy/srim/srimdb.py
irradiapy/srim/ofiles/__init__.py
irradiapy/srim/ofiles/backscat.py
irradiapy/srim/ofiles/collision.py
irradiapy/srim/ofiles/e2recoil.py
irradiapy/srim/ofiles/ioniz.py
irradiapy/srim/ofiles/lateral.py
irradiapy/srim/ofiles/novac.py
irradiapy/srim/ofiles/phonon.py
irradiapy/srim/ofiles/range.py
irradiapy/srim/ofiles/range3d.py
irradiapy/srim/ofiles/sputter.py
irradiapy/srim/ofiles/srimfile.py
irradiapy/srim/ofiles/subcollision.py
irradiapy/srim/ofiles/transmit.py
irradiapy/srim/ofiles/trimdat.py
irradiapy/srim/ofiles/vacancy.py
irradiapy/srim/target/__init__.py
irradiapy/srim/target/element.py
irradiapy/srim/target/layer.py
irradiapy/srim/target/target.py
irradiapy/styles/latex.mplstyle
irradiapy/styles/nolatex.mplstyle
irradiapy/utils/__init__.py
irradiapy/utils/io.py
irradiapy/utils/math.py
irradiapy/utils/mpi.py
irradiapy/utils/sqlite.py
irradiapy-1.0.1.dist-info/licenses/LICENSE
irradiapy-1.0.1.dist-info/METADATA
irradiapy-1.0.1.dist-info/WHEEL
irradiapy-1.0.1.dist-info/top_level.txt
irradiapy-1.0.1.dist-info/RECORD
