Metadata-Version: 2.4
Name: irradiapy
Version: 1.0.1
Summary: This Python package is aimed towards the simulation and analysis of irradiation damage with multiple tools.
Author-email: "Gutiérrez-Camacho, A.-C." <abel.gutierrez@ua.es>
License: MIT
Requires-Python: >=3.10.0
License-File: LICENSE
Requires-Dist: matplotlib>=3.10.1
Requires-Dist: numpy>=2.2.4
Requires-Dist: PyGetWindow>=0.0.9
Requires-Dist: pywinauto>=0.6.8
Requires-Dist: scikit_learn>=1.6.0
Requires-Dist: scipy>=1.14.1
Requires-Dist: mpi4py>=3.0.0
Dynamic: license-file
